tools_for_tl_glow_curves/Initial_rise_TL.py
tools_for_tl_glow_curves/TL_peak_parameters.py
tools_for_tl_glow_curves/__init__.py
tools_for_tl_glow_curves/energy_activation_peak_parameters.py
tools_for_tl_glow_curves/energy_activation_peak_position.py
tools_for_tl_glow_curves-1.0.1.dist-info/licenses/LICENSE
tools_for_tl_glow_curves-1.0.1.dist-info/METADATA
tools_for_tl_glow_curves-1.0.1.dist-info/WHEEL
tools_for_tl_glow_curves-1.0.1.dist-info/top_level.txt
tools_for_tl_glow_curves-1.0.1.dist-info/RECORD
