Metadata-Version: 2.4
Name: tools_for_tl_glow_curves
Version: 1.0.1
Summary: Python tools for analyzing Thermoluminescence (TL) glow curves
Author: Jorge Eduardo Tenopala Peralta
License: MIT
Requires-Python: >=3.8
License-File: LICENSE
Requires-Dist: numpy
Requires-Dist: matplotlib
Requires-Dist: pandas
Requires-Dist: scikit-learn
Requires-Dist: ipython
Dynamic: license-file
